setup.py
malyxm.egg-info/PKG-INFO
malyxm.egg-info/SOURCES.txt
malyxm.egg-info/dependency_links.txt
malyxm.egg-info/top_level.txt
pakiet_testowy/__init__.py
pakiet_testowy/dzialanie.py