Metadata-Version: 2.1
Name: malyxm
Version: 1.0
Summary: pakiet testowy
Home-page: http://sda.com
License: UNKNOWN
Platform: UNKNOWN
